WinKeyBoard/VK.py
WinKeyBoard/__init__.py
WinKeyBoard/key_controller.py
WinKeyBoard/type_conversion.py
WinKeyBoard-0.1.2.dist-info/LICENSE
WinKeyBoard-0.1.2.dist-info/METADATA
WinKeyBoard-0.1.2.dist-info/WHEEL
WinKeyBoard-0.1.2.dist-info/top_level.txt
WinKeyBoard-0.1.2.dist-info/RECORD
