Metadata-Version: 2.1
Name: WinKeyBoard
Version: 0.1.2
Summary: Windows下的键盘控制
Home-page: https://github.com/AWangDog/WinKeyBoard
Author: AWang_Dog
Author-email: AWangDog@126.com
Classifier: Programming Language :: Python :: 3
Classifier: License :: OSI Approved :: MIT License
Classifier: Operating System :: Microsoft :: Windows
Requires-Python: >=3.9
License-File: LICENSE
